{"nodes": [{"id": "discord_notify", "label": "discord_notify.py", "file_type": "code", "source_file": "tools\\discord_notify.py", "source_location": "L1"}, {"id": "discord_notify_send_discord_message", "label": "send_discord_message()", "file_type": "code", "source_file": "tools\\discord_notify.py", "source_location": "L13"}, {"id": "discord_notify_rationale_1", "label": "Tool: Discord Notify Envia mensagens para um canal Discord via OpenClaw Gateway", "file_type": "rationale", "source_file": "tools\\discord_notify.py", "source_location": "L1"}, {"id": "discord_notify_rationale_14", "label": "Envia uma mensagem para um canal Discord via OpenClaw Gateway REST API.", "file_type": "rationale", "source_file": "tools\\discord_notify.py", "source_location": "L14"}], "edges": [{"source": "discord_notify", "target": "os", "relation": "imports", "confidence": "EXTRACTED", "source_file": "tools\\discord_notify.py", "source_location": "L6", "weight": 1.0}, {"source": "discord_notify", "target": "requests", "relation": "imports", "confidence": "EXTRACTED", "source_file": "tools\\discord_notify.py", "source_location": "L7", "weight": 1.0}, {"source": "discord_notify", "target": "discord_notify_send_discord_message", "relation": "contains", "confidence": "EXTRACTED", "source_file": "tools\\discord_notify.py", "source_location": "L13", "weight": 1.0}, {"source": "discord_notify_rationale_1", "target": "discord_notify", "relation": "rationale_for", "confidence": "EXTRACTED", "source_file": "tools\\discord_notify.py", "source_location": "L1", "weight": 1.0}, {"source": "discord_notify_rationale_14", "target": "discord_notify_send_discord_message", "relation": "rationale_for", "confidence": "EXTRACTED", "source_file": "tools\\discord_notify.py", "source_location": "L14", "weight": 1.0}]}