{"nodes": [{"id": "env", "label": "env.py", "file_type": "code", "source_file": "mcps\\trends_mcp\\migrations\\env.py", "source_location": "L1"}, {"id": "env_include_object", "label": "include_object()", "file_type": "code", "source_file": "mcps\\trends_mcp\\migrations\\env.py", "source_location": "L26"}, {"id": "env_run_migrations_offline", "label": "run_migrations_offline()", "file_type": "code", "source_file": "mcps\\trends_mcp\\migrations\\env.py", "source_location": "L36"}, {"id": "env_run_migrations_online", "label": "run_migrations_online()", "file_type": "code", "source_file": "mcps\\trends_mcp\\migrations\\env.py", "source_location": "L52"}, {"id": "env_rationale_27", "label": "Bloqueia qualquer intera\u00e7\u00e3o com tabelas de outros schemas.", "file_type": "rationale", "source_file": "mcps\\trends_mcp\\migrations\\env.py", "source_location": "L27"}], "edges": [{"source": "env", "target": "sys", "relation": "imports", "confidence": "EXTRACTED", "source_file": "mcps\\trends_mcp\\migrations\\env.py", "source_location": "L1", "weight": 1.0}, {"source": "env", "target": "os", "relation": "imports", "confidence": "EXTRACTED", "source_file": "mcps\\trends_mcp\\migrations\\env.py", "source_location": "L2", "weight": 1.0}, {"source": "env", "target": "logging_config", "relation": "imports_from", "confidence": "EXTRACTED", "source_file": "mcps\\trends_mcp\\migrations\\env.py", "source_location": "L3", "weight": 1.0}, {"source": "env", "target": "sqlalchemy", "relation": "imports_from", "confidence": "EXTRACTED", "source_file": "mcps\\trends_mcp\\migrations\\env.py", "source_location": "L4", "weight": 1.0}, {"source": "env", "target": "alembic", "relation": "imports_from", "confidence": "EXTRACTED", "source_file": "mcps\\trends_mcp\\migrations\\env.py", "source_location": "L5", "weight": 1.0}, {"source": "env", "target": "env_include_object", "relation": "contains", "confidence": "EXTRACTED", "source_file": "mcps\\trends_mcp\\migrations\\env.py", "source_location": "L26", "weight": 1.0}, {"source": "env", "target": "env_run_migrations_offline", "relation": "contains", "confidence": "EXTRACTED", "source_file": "mcps\\trends_mcp\\migrations\\env.py", "source_location": "L36", "weight": 1.0}, {"source": "env", "target": "env_run_migrations_online", "relation": "contains", "confidence": "EXTRACTED", "source_file": "mcps\\trends_mcp\\migrations\\env.py", "source_location": "L52", "weight": 1.0}, {"source": "env_rationale_27", "target": "env_include_object", "relation": "rationale_for", "confidence": "EXTRACTED", "source_file": "mcps\\trends_mcp\\migrations\\env.py", "source_location": "L27", "weight": 1.0}]}